{"cameraMode":{"drawMode":0,"name":"Shaded","section":"Shading Mode"},"sceneLighting":false,"audioPlay":false,"sceneViewState":{"m_AlwaysRefresh":false,"showFog":true,"showSkybox":false,"showFlares":true,"showImageEffects":true,"showParticleSystems":true,"showVisualEffectGraphs":true,"m_FxEnabled":true},"in2DMode":false,"pivot":{"x":-1.7830162048339844,"y":-9.710899353027344,"z":15.051776885986329},"rotation":{"x":-0.264361709356308,"y":0.048972778022289279,"z":-0.012764658778905869,"w":-0.9633031487464905},"size":11.38855266571045,"orthographic":false}